pycity_base/__init__.py
pycity_base/classes/__init__.py
pycity_base/classes/building.py
pycity_base/classes/city_district.py
pycity_base/classes/environment.py
pycity_base/classes/heating_curve.py
pycity_base/classes/prices.py
pycity_base/classes/sun.py
pycity_base/classes/timer.py
pycity_base/classes/weather.py
pycity_base/classes/demand/__init__.py
pycity_base/classes/demand/apartment.py
pycity_base/classes/demand/domestic_hot_water.py
pycity_base/classes/demand/electrical_demand.py
pycity_base/classes/demand/load.py
pycity_base/classes/demand/occupancy.py
pycity_base/classes/demand/room.py
pycity_base/classes/demand/space_cooling.py
pycity_base/classes/demand/space_heating.py
pycity_base/classes/demand/zone_inputs.py
pycity_base/classes/demand/zone_parameters.py
pycity_base/classes/supply/__init__.py
pycity_base/classes/supply/absorption_chiller.py
pycity_base/classes/supply/battery.py
pycity_base/classes/supply/boiler.py
pycity_base/classes/supply/building_energy_system.py
pycity_base/classes/supply/combined_heat_power.py
pycity_base/classes/supply/compression_chiller.py
pycity_base/classes/supply/cooling_device.py
pycity_base/classes/supply/electrical_heater.py
pycity_base/classes/supply/heat_pump.py
pycity_base/classes/supply/heating_device.py
pycity_base/classes/supply/inverter.py
pycity_base/classes/supply/photovoltaic.py
pycity_base/classes/supply/thermal_energy_storage.py
pycity_base/classes/supply/wind_energy_converter.py
pycity_base/examples/__init__.py
pycity_base/examples/example_absorption_chiller.py
pycity_base/examples/example_apartment.py
pycity_base/examples/example_battery.py
pycity_base/examples/example_boiler.py
pycity_base/examples/example_building.py
pycity_base/examples/example_building_energy_system.py
pycity_base/examples/example_city_disctrict.py
pycity_base/examples/example_city_district_stoch.py
pycity_base/examples/example_combined_heat_power.py
pycity_base/examples/example_compression_chiller.py
pycity_base-0.3.3.dist-info/METADATA
pycity_base-0.3.3.dist-info/WHEEL
pycity_base-0.3.3.dist-info/top_level.txt
pycity_base-0.3.3.dist-info/RECORD
